<?xml version="1.0" encoding="utf-8"?>
<XnaContent>
  <Asset Type="ProjectMercury.ParticleEffect">
    <Item>
      <Name>Basic Emitter</Name>
      <Budget>5000</Budget>
      <Term>2</Term>
      <ReleaseQuantity>80</ReleaseQuantity>
      <Enabled>True</Enabled>
      <ReleaseSpeed>
        <Value>100</Value>
        <Variation>80</Variation>
      </ReleaseSpeed>
      <ReleaseColour>
        <Value>1 0 0</Value>
        <Variation>0 0 0</Variation>
      </ReleaseColour>
      <ReleaseOpacity>
        <Value>0</Value>
        <Variation>0</Variation>
      </ReleaseOpacity>
      <ReleaseScale>
        <Value>64</Value>
        <Variation>32</Variation>
      </ReleaseScale>
      <ReleaseRotation>
        <Value>0</Value>
        <Variation>0</Variation>
      </ReleaseRotation>
      <ReleaseImpulse>0 0</ReleaseImpulse>
      <ParticleTextureAssetName>.\particles\assets\FlowerBurst</ParticleTextureAssetName>
      <Modifiers>
        <Item Type="ProjectMercury.Modifiers.OpacityInterpolatorModifier">
          <InitialOpacity>1</InitialOpacity>
          <MiddleOpacity>1</MiddleOpacity>
          <MiddlePosition>0</MiddlePosition>
          <FinalOpacity>0</FinalOpacity>
        </Item>
        <Item Type="ProjectMercury.Modifiers.DampingModifier">
          <DampingCoefficient>0.4</DampingCoefficient>
        </Item>
      </Modifiers>
      <BlendMode>Alpha</BlendMode>
      <TriggerOffset>0 0</TriggerOffset>
      <MinimumTriggerPeriod>0</MinimumTriggerPeriod>
    </Item>
    <Name>Particle Effect</Name>
    <Author />
    <Description />
  </Asset>
</XnaContent>